Metadata-Version: 2.4
Name: toy-gpt-train-100-unigram
Version: 0.9.6
Summary: Toy GPT next-token prediction using a unigram model.
Author-email: Denise Case <dcase@nwmissouri.edu>
Project-URL: Documentation, https://toy-gpt.github.io/train-100-unigram/
Project-URL: Issues, https://github.com/toy-gpt/train-100-unigram/issues
Project-URL: Repository, https://github.com/toy-gpt/train-100-unigram
Keywords: toy,gpt,training,unigram,language model
Classifier: Development Status :: 4 - Beta
Classifier: License :: OSI Approved :: MIT License
Classifier: Natural Language :: English
Classifier: Operating System :: OS Independent
Classifier: Programming Language :: Python :: 3 :: Only
Classifier: Programming Language :: Python :: 3.14
Classifier: Topic :: Scientific/Engineering :: Artificial Intelligence
Classifier: Topic :: Education
Classifier: Topic :: Software Development :: Libraries
Classifier: Intended Audience :: Developers
Classifier: Intended Audience :: Education
Classifier: Typing :: Typed
Requires-Python: >=3.14
License-File: LICENSE
Requires-Dist: datafun-toolkit>=0.9.5
Provides-Extra: dev
Requires-Dist: bandit>=1.9.3; extra == "dev"
Requires-Dist: deptry>=0.10.1; extra == "dev"
Requires-Dist: packaging>=25.0; extra == "dev"
Requires-Dist: pre-commit>=4.5.1; extra == "dev"
Requires-Dist: pytest>=9.0.2; extra == "dev"
Requires-Dist: pytest-cov>=7.0.0; extra == "dev"
Requires-Dist: pyright>=1.1.408; extra == "dev"
Requires-Dist: ruff>=0.14.13; extra == "dev"
Requires-Dist: twine>=6.2.0; extra == "dev"
Requires-Dist: validate-pyproject>=0.24.1; extra == "dev"
Provides-Extra: docs
Requires-Dist: mike>=2.1.3; extra == "docs"
Requires-Dist: mkdocs>=1.6.1; extra == "docs"
Requires-Dist: mkdocs-material>=9.7.1; extra == "docs"
Requires-Dist: mkdocs-static-i18n>=1.3.0; extra == "docs"
Requires-Dist: mkdocstrings[python]>=1.0.0; extra == "docs"
Dynamic: license-file
